google_labs_html_chunker/__init__.py
google_labs_html_chunker/html_chunker.py
google_labs_html_chunker-0.0.4.dist-info/METADATA
google_labs_html_chunker-0.0.4.dist-info/WHEEL
google_labs_html_chunker-0.0.4.dist-info/licenses/LICENSE
google_labs_html_chunker-0.0.4.dist-info/RECORD
