Metadata-Version: 2.1
Name: google_labs_html_chunker
Version: 0.0.4
Summary: A library to chunk HTML web pages into plain text passages.
Author-email: Google Labs <labs-pypi@google.com>
License-File: LICENSE
Classifier: License :: OSI Approved :: Apache Software License
Classifier: Operating System :: OS Independent
Classifier: Programming Language :: Python :: 3
Requires-Python: >=3.6
Requires-Dist: beautifulsoup4>=4.12.2
Requires-Dist: html5lib>=1.1
